CHANGES.rst
HekaPy.spec
MANIFEST.in
README.rst
setup.py
docs/Makefile
docs/source/conf.py
docs/source/config.rst
docs/source/getstarted.rst
docs/source/index.rst
docs/source/api/client.rst
docs/source/api/config.rst
docs/source/api/decorators.rst
docs/source/api/encoders.rst
docs/source/api/exceptions.rst
docs/source/api/filters.rst
docs/source/api/streams.rst
heka/__init__.py
heka/client.py
heka/command.py
heka/config.py
heka/encoders.py
heka/exceptions.py
heka/filters.py
heka/holder.py
heka/logging.py
heka/message.py
heka/message_pb2.py
heka/path.py
heka/util.py
heka/decorators/__init__.py
heka/decorators/base.py
heka/decorators/stats.py
heka/decorators/util.py
heka/streams/__init__.py
heka/streams/dev.py
heka/streams/logging.py
heka/streams/tcp.py
heka/streams/udp.py
heka/tests/__init__.py
heka/tests/helpers.py
heka/tests/plugin.py
heka/tests/plugin_exception.py
heka/tests/sync_subscriber.py
heka/tests/test_client.py
heka/tests/test_config.py
heka/tests/test_decorators.py
heka/tests/test_encoders.py
heka/tests/test_filters.py
heka/tests/test_hmac.py
heka/tests/test_logging.py
heka/tests/test_protobuf.py
heka/tests/test_streams.py
heka/tests/test_timer.py
heka_py.egg-info/PKG-INFO
heka_py.egg-info/SOURCES.txt
heka_py.egg-info/dependency_links.txt
heka_py.egg-info/entry_points.txt
heka_py.egg-info/not-zip-safe
heka_py.egg-info/requires.txt
heka_py.egg-info/top_level.txt