Metadata-Version: 1.1
Name: heka-py
Version: 0.30.3
Summary: Metrics Logging
Home-page: https://github.com/mozilla-services/heka-py
Author: Rob Miller
Author-email: rmiller@mozilla.com
License: MPLv2.0
Keywords: heka metrics logging client
Platform: UNKNOWN
Classifier: License :: OSI Approved :: Mozilla Public License 2.0 (MPL 2.0)
